{
   "166" : {
      "dialog" : {
         "0" : {
            "NeedResponse" : "1",
            "text" : "DESC_CHANGE[0] - 166"
         },
         "1" : {
            "NeedResponse" : "1",
            "text" : "DESC_CHANGE[1] - 166"
         },
         "2" : {
            "NeedResponse" : "1",
            "text" : "DESC_CHANGE[2] - 166"
         },
         "3" : {
            "NeedResponse" : "1",
            "text" : "DESC_CHANGE[3] - 166"
         },
         "4" : {
            "NeedResponse" : "1",
            "text" : "DESC_CHANGE[4] - 166"
         },
         "5" : {
            "NeedResponse" : "1",
            "text" : "DESC_CHANGE[5] - 166"
         },
         "6" : {
            "NeedResponse" : "1",
            "text" : "DESC_CHANGE[6] - 166"
         },
         "7" : {
            "NeedResponse" : "1",
            "text" : "DESC_CHANGE[7] - 166"
         },
         "8" : {
            "NeedResponse" : "1",
            "text" : "DESC_CHANGE[8] - 166"
         },
         "9" : {
            "NeedResponse" : "1",
            "text" : "DESC_CHANGE[9] - 166"
         }
      },
      "name" : "NEED TO CHANGE - 166",
      "no" : {
         "0" : {
            "gold" : "-100",
            "happiness" : "-100",
            "population" : "-100",
            "text" : "NO[0] TO CHANGE - 166"
         },
         "1" : {
            "gold" : "-100",
            "happiness" : "-100",
            "population" : "-100",
            "text" : "NO[1] TO CHANGE - 166"
         },
         "2" : {
            "gold" : "-100",
            "happiness" : "-100",
            "population" : "-100",
            "text" : "NO[2] TO CHANGE - 166"
         },
         "3" : {
            "gold" : "-100",
            "happiness" : "-100",
            "population" : "-100",
            "text" : "NO[3] TO CHANGE - 166"
         },
         "4" : {
            "gold" : "-100",
            "happiness" : "-100",
            "population" : "-100",
            "text" : "NO[4] TO CHANGE - 166"
         },
         "5" : {
            "gold" : "-100",
            "happiness" : "-100",
            "population" : "-100",
            "text" : "NO[5] TO CHANGE - 166"
         },
         "6" : {
            "gold" : "-100",
            "happiness" : "-100",
            "population" : "-100",
            "text" : "NO[6] TO CHANGE - 166"
         },
         "7" : {
            "gold" : "-100",
            "happiness" : "-100",
            "population" : "-100",
            "text" : "NO[7] TO CHANGE - 166"
         },
         "8" : {
            "gold" : "-100",
            "happiness" : "-100",
            "population" : "-100",
            "text" : "NO[8] TO CHANGE - 166"
         },
         "9" : {
            "gold" : "-100",
            "happiness" : "-100",
            "population" : "-100",
            "text" : "NO[9] TO CHANGE - 166"
         }
      },
      "yes" : {
         "0" : {
            "gold" : "100",
            "happiness" : "100",
            "population" : "100",
            "text" : "YES[0] TO CHANGE - 166"
         },
         "1" : {
            "gold" : "100",
            "happiness" : "100",
            "population" : "100",
            "text" : "YES[1] TO CHANGE - 166"
         },
         "2" : {
            "gold" : "100",
            "happiness" : "100",
            "population" : "100",
            "text" : "YES[2] TO CHANGE - 166"
         },
         "3" : {
            "gold" : "100",
            "happiness" : "100",
            "population" : "100",
            "text" : "YES[3] TO CHANGE - 166"
         },
         "4" : {
            "gold" : "100",
            "happiness" : "100",
            "population" : "100",
            "text" : "YES[4] TO CHANGE - 166"
         },
         "5" : {
            "gold" : "100",
            "happiness" : "100",
            "population" : "100",
            "text" : "YES[5] TO CHANGE - 166"
         },
         "6" : {
            "gold" : "100",
            "happiness" : "100",
            "population" : "100",
            "text" : "YES[6] TO CHANGE - 166"
         },
         "7" : {
            "gold" : "100",
            "happiness" : "100",
            "population" : "100",
            "text" : "YES[7] TO CHANGE - 166"
         },
         "8" : {
            "gold" : "100",
            "happiness" : "100",
            "population" : "100",
            "text" : "YES[8] TO CHANGE - 166"
         },
         "9" : {
            "gold" : "100",
            "happiness" : "100",
            "population" : "100",
            "text" : "YES[9] TO CHANGE - 166"
         }
      }
   }
}
